package/__init__.py
package/main.py
tronlix-0.0.1.dist-info/licenses/LICENSE.txt
tronlix-0.0.1.dist-info/METADATA
tronlix-0.0.1.dist-info/WHEEL
tronlix-0.0.1.dist-info/top_level.txt
tronlix-0.0.1.dist-info/RECORD
