Metadata-Version: 2.4
Name: tronlix
Version: 0.0.1
Summary: tronlix library for Python
Author: troninbon
Author-email: e0929096@gmail.com
License: MIT
Project-URL: Source Repository, https://github.com
License-File: LICENSE.txt
Requires-Dist: requests
Dynamic: author
Dynamic: author-email
Dynamic: description-content-type
Dynamic: license
Dynamic: license-file
Dynamic: project-url
Dynamic: requires-dist
Dynamic: summary
